Workbook
Name FX_RATE: Assumptions!$B$5
Name BATCH_SIZE: Assumptions!$B$6
Name PLATFORM_FEE: Assumptions!$B$7
Name SELL_PRICE: Assumptions!$B$8
Name BOM_MIDPOINT: BOM!$D$10
Name NRE_PER_UNIT_MID: NRE!$B$11

Sheet Assumptions
A1: Ori — Pricing Assumptions
A2: Edit the yellow cells — every other sheet recalculates from these.
A4: Assumption | B4: Value | C4: Notes
A5: FX rate (1 USD in CAD) | B5: 1.41 | C5: Bank of Canada / US Fed H.10, 2026-07-11
A6: Batch size (units) | B6: 100 | C6: Initial pilot batch
A7: Platform + payment processing fee (%) | B7: 0.09 | C7: Kickstarter/Indiegogo blended ~8-10%
A8: Chosen sell price (CAD) | B8: 150 | C8: Set below the direct-comp floor (see Market Comps)

Sheet BOM
A1: Ori — Bill of Materials (per unit @ qty 100)
A2: Status: working estimate, not a supplier quote, except the confirmed line below.
A4: Component | B4: Low (CAD) | C4: High (CAD) | D4: Midpoint (CAD) | E4: Low (USD) | F4: High (USD) | G4: Status
A5: Waveshare ESP32-S3-Touch-LCD-4.3 module (16MB flash/8MB PSRAM, GT911 touch, CH422G, ST7701 LCD, USB-C) | B5: 38.59 | C5: 38.59 | D5: =AVERAGE(B5:C5) | E5: =B5/Assumptions!$B$5 | F5: =C5/Assumptions!$B$5 | G5: Confirmed quote
A6: Enclosure — in-house FDM 3D print (filament + print time + post-processing labor) | B6: 9 | C6: 15 | D6: =AVERAGE(B6:C6) | E6: =B6/Assumptions!$B$5 | F6: =C6/Assumptions!$B$5 | G6: Estimate
A7: Feet, screws, stand hardware | B7: 1 | C7: 3 | D7: =AVERAGE(B7:C7) | E7: =B7/Assumptions!$B$5 | F7: =C7/Assumptions!$B$5 | G7: Estimate
A8: Retail packaging (box, insert, quick-start card) | B8: 4 | C8: 7 | D8: =AVERAGE(B8:C8) | E8: =B8/Assumptions!$B$5 | F8: =C8/Assumptions!$B$5 | G8: Estimate
A9: Assembly + firmware flash + QC labor (~20-25 min/unit) | B9: 8 | C9: 14 | D9: =AVERAGE(B9:C9) | E9: =B9/Assumptions!$B$5 | F9: =C9/Assumptions!$B$5 | G9: Estimate
A10: TOTAL — per-unit landed cost | B10: =SUM(B5:B9) | C10: =SUM(C5:C9) | D10: =AVERAGE(B10:C10) | E10: =B10/Assumptions!$B$5 | F10: =C10/Assumptions!$B$5
A12: Explicitly excluded (decided in planning):
A13: • LiPo backup battery — skipped. hardware.md specs firmware/UI to behave as if no battery exists.
A14: • USB-C cable — not shipped (BYO-cable).
A15: • USB-C wall adapter — not shipped (BYO-charger).

Sheet NRE
A1: Ori — One-Time Costs (NRE)
A2: Not per-unit. Amortized across the batch size set in Assumptions.
A4: Item | B4: Low (CAD) | C4: High (CAD) | D4: Notes
A5: FCC / ISED / CE certification | B5: 2800 | C5: 5600 | D5: Reduced scope — ESP32-S3 module carries Espressif's own modular radio grant. Finished-product filing still needs Part 15B unintentional-emissions testing on the assembled device + verification the module was integrated per its grant conditions. Every wireless competitor (TRMNL, Divoom, Skylight, Kuando) filed for the assembled device, not just the radio chip.
A6: Enclosure tooling | B6: 0 | C6: 0 | D6: In-house FDM 3D printing — no CNC programming or injection-mold tooling for this batch.
A7: TOTAL NRE | B7: =SUM(B5:B6) | C7: =SUM(C5:C6)
A9: Amortized per unit (low) | B9: =B7/Assumptions!$B$6
A10: Amortized per unit (high) | B10: =C7/Assumptions!$B$6
A11: Amortized per unit (midpoint) | B11: =AVERAGE(B9:B10)

Sheet Market Comps
A1: Ori — Market Comps (converted to CAD)
A2: FX rate pulled live from Assumptions sheet.
A4: Product | B4: Category | C4: Radio | D4: Price CAD (low) | E4: Price CAD (high) | F4: Certified?
A5: Luxafor Flag | B5: Presence light, no display | C5: None (wired USB) | D5: 61 | E5: 61 | F5: N/A (no radiator)
A6: Kuando Busylight | B6: Presence light, no display | C6: Yes | D6: 66 | E6: 78 | F6: FCC 2AYIK1582
A7: Divoom Times Gate | B7: Desk info display (clock/weather/notifs) | C7: WiFi | D7: 183 | E7: 212 | F7: FCC A8I-TIMES-GATE
A8: TRMNL (OG) | B8: 7.5" e-ink desk dashboard, indie | C8: WiFi | D8: 196 | E8: 217 | F8: FCC 2BFWO-OG
A9: Divoom Ditoo | B9: Pixel display + speaker | C9: BT | D9: 226 | E9: 226 | F9: Yes (Divoom A8I grantee)
A10: Skylight Calendar (15") | B10: Large touchscreen family hub + subscription | C10: WiFi | D10: 268 | E10: 282 | F10: FCC 2AABK-150
A11: TRMNL X | B11: 10.3" e-ink, larger | C11: WiFi | D11: 309 | E11: 309 | F11: —
A13: Ori's honest peer group: Divoom Times Gate / TRMNL tier (~C$183-217) — small desk companion display, calendar/status/notifications, no forced subscription, indie/first-batch.

Sheet Pricing Waterfall
A1: Ori — Per-Unit Profit Waterfall
A2: Sell price, fee %, batch size, and FX all pull live from Assumptions.
A4: Line | B4: Amount (CAD) | C4: Running total (CAD)
A5: Sell price | B5: =Assumptions!$B$8 | C5: =B5
A6: BOM (midpoint) | B6: =-BOM!$D$10 | C6: =C5+B6
A7: Gross margin % (before fees/NRE) | B7: =C6/Assumptions!$B$8
A8: Crowdfunding platform + payment fees | B8: =-Assumptions!$B$8*Assumptions!$B$7 | C8: =C6+B8
A9: NRE amortization (certification, midpoint) | B9: =-NRE!$B$11 | C9: =C8+B9
A10: NET PER UNIT (backer pays shipping) | C10: =C9
A12: NET OVER BATCH | C12: =C10*Assumptions!$B$6
A14: Key insight — certification is the margin killer at 100 units, not the BOM. Spreading C$2,800-5,600 of certification across only 100 units costs C$28-56/unit. Three ways to handle it: (1) treat certification as R&D recovered over future batches — recommended if the goal is validation; (2) run a larger campaign (300-500 units) so certification amortizes to C$6-19/unit; (3) beta/founder batch, uncertified, sold informally to friends/early adopters only.

Sheet Alternative Prices
A1: Ori — Alternative Price Points
A2: Gross margin vs. BOM midpoint, before platform fees / NRE.
A4: Price (CAD) | B4: Gross margin % | C4: Note
A5: 150 | B5: =(A5-BOM!$D$10)/A5 | C5: Chosen. Undercuts entire comp tier; thin after NRE at 100 units.
A6: 179 | B6: =(A6-BOM!$D$10)/A6 | C6: Smallest bump giving real headroom for NRE/shipping/returns; still under every comp.
A7: 199 | B7: =(A7-BOM!$D$10)/A7 | C7: Standard DTC-hardware margin; aligns with Times Gate/TRMNL comp tier.

Sheet Open Items
A1: Ori — Open Items Before Finalizing
A2: Checklist.
A4: ☐ Get real quotes for the soft-estimate lines: enclosure filament/labor, packaging, hardware kit.
A5: ☐ Confirm assembly/QC labor rate against actual per-unit build time.
A6: ☐ Get a firm certification quote from an accredited lab (FCC + ISED bundle) — this dominates the NRE and the batch-one margin.
A7: ☐ Decide certification strategy (R&D-amortized / larger batch / uncertified beta).
A8: ☐ Re-check FX before committing to USD purchase orders.
